django_robokassa3-1.4.dist-info/METADATA
django_robokassa3-1.4.dist-info/RECORD
django_robokassa3-1.4.dist-info/WHEEL
django_robokassa3-1.4.dist-info/top_level.txt
robokassa/__init__.py
robokassa/conf.py
robokassa/forms.py
robokassa/models.py
robokassa/signals.py
robokassa/tests.py
robokassa/urls.py
robokassa/views.py
robokassa/migrations/0001_initial.py
robokassa/migrations/__init__.py
