Metadata-Version: 2.1
Name: django-robokassa3
Version: 1.4
Summary: Приложение для интеграции платежной системы ROBOKASSA в проекты на Django.
Home-page: https://github.com/mpyrev/django-robokassa
Author: Mikhail Pyrev
Author-email: mikhail.pyrev@gmail.com
License: MIT License
Platform: UNKNOWN
Classifier: Environment :: Web Environment
Classifier: Framework :: Django
Classifier: Framework :: Django :: 1.11
Classifier: Framework :: Django :: 2.0
Classifier: Intended Audience :: Developers
Classifier: License :: OSI Approved :: MIT License
Classifier: Programming Language :: Python
Classifier: Programming Language :: Python :: 2
Classifier: Programming Language :: Python :: 2.7
Classifier: Programming Language :: Python :: 3
Classifier: Programming Language :: Python :: 3.4
Classifier: Programming Language :: Python :: 3.5
Classifier: Programming Language :: Python :: 3.6
Classifier: Programming Language :: Python :: 3.7
Classifier: Topic :: Software Development :: Libraries :: Python Modules
Classifier: Natural Language :: Russian
Requires-Dist: Django (>=1.11)
Requires-Dist: six
